profpy/__init__.py
profpy/__main__.py
profpy/apis/BlackBoardLearn.py
profpy/apis/ServiceNowTable.py
profpy/apis/TwentyFiveLive.py
profpy/apis/__init__.py
profpy/apis/utils/Api.py
profpy/apis/utils/Token.py
profpy/apis/utils/__init__.py
profpy/apis/utils/exceptions.py
profpy/cli/__init__.py
profpy/cli/flask_init/__init__.py
profpy/cli/flask_init/files/cli.Dockerfile
profpy/cli/flask_init/files/cli.README.md
profpy/cli/flask_init/files/cli.SAMPLE.env
profpy/cli/flask_init/files/cli.asset_config.txt
profpy/cli/flask_init/files/cli.db_user.ddl.sql
profpy/cli/flask_init/files/cli.dev.Dockerfile
profpy/cli/flask_init/files/cli.dev.docker-compose.override.yml
profpy/cli/flask_init/files/cli.docker-compose.yml
profpy/cli/flask_init/files/cli.favicon.ico
profpy/cli/flask_init/files/cli.gitignore
profpy/cli/flask_init/files/cli.index.html
profpy/cli/flask_init/files/cli.layout.html
profpy/cli/flask_init/files/cli.main.css
profpy/cli/flask_init/files/cli.main.py
profpy/cli/flask_init/files/cli.prod.docker-compose.override.yml
profpy/cli/flask_init/files/cli.requirements.txt
profpy/cli/flask_init/files/cli.rowan-site.css
profpy/cli/flask_init/files/cli.rowan_torch_logo_small.png
profpy/cli/flask_init/files/cli.setup.sh
profpy/cli/flask_init/files/cli.test.docker-compose.override.yml
profpy/cli/logs/__init__.py
profpy/cli/run_app/__init__.py
profpy/cli/stop_app/__init__.py
profpy/db/__init__.py
profpy/db/general/__init__.py
profpy/db/general/connections.py
profpy/db/general/functions.py
profpy/web/__init__.py
profpy/web/web.py
profpy-3.2.1.dist-info/licenses/LICENSE
profpy-3.2.1.dist-info/METADATA
profpy-3.2.1.dist-info/WHEEL
profpy-3.2.1.dist-info/entry_points.txt
profpy-3.2.1.dist-info/top_level.txt
profpy-3.2.1.dist-info/RECORD
