Metadata-Version: 2.4
Name: profpy
Version: 3.2.1
Home-page: https://github.com/rowanuniversity/profpy/
Author: Connor Hornibrook
Author-email: hornibrookc@rowan.edu
License: MIT
Requires-Python: >=3.6.7
License-File: LICENSE
Requires-Dist: oracledb==2.0.1
Requires-Dist: requests>=2.25.1
Requires-Dist: Flask>=1.1.1
Requires-Dist: caslib.py>=2.2.2
Requires-Dist: sqlalchemy==2.0.27
Requires-Dist: jinja2>=2.10.3
Requires-Dist: greenlet==2.0.2
Requires-Dist: ldap3==2.9.1
Dynamic: author
Dynamic: author-email
Dynamic: description
Dynamic: description-content-type
Dynamic: home-page
Dynamic: license
Dynamic: license-file
Dynamic: requires-dist
Dynamic: requires-python
